cvt_test_ms/__init__.py
cvt_test_ms/converter.py
cvt_test_ms-1.0.1.dist-info/LICENSE
cvt_test_ms-1.0.1.dist-info/METADATA
cvt_test_ms-1.0.1.dist-info/WHEEL
cvt_test_ms-1.0.1.dist-info/top_level.txt
cvt_test_ms-1.0.1.dist-info/RECORD
